{
	"configurations" : 
	[
		{
			"directories" : 
			[
				{
					"build" : ".",
					"hasInstallRule" : true,
					"jsonFile" : "directory-.-Debug-18f9d90151133e633c46.json",
					"minimumCMakeVersion" : 
					{
						"string" : "3.16"
					},
					"projectIndex" : 0,
					"source" : ".",
					"targetIndexes" : 
					[
						0,
						1,
						2,
						3,
						4,
						5,
						6,
						7,
						8,
						9,
						10,
						11,
						12,
						13,
						14,
						15
					]
				}
			],
			"name" : "Debug",
			"projects" : 
			[
				{
					"directoryIndexes" : 
					[
						0
					],
					"name" : "Recipe-Manager",
					"targetIndexes" : 
					[
						0,
						1,
						2,
						3,
						4,
						5,
						6,
						7,
						8,
						9,
						10,
						11,
						12,
						13,
						14,
						15
					]
				}
			],
			"targets" : 
			[
				{
					"directoryIndex" : 0,
					"id" : "all_aotstats::@6890427a1f51a3e7e1df",
					"jsonFile" : "target-all_aotstats-Debug-d187ab4427282f8331b0.json",
					"name" : "all_aotstats",
					"projectIndex" : 0
				},
				{
					"directoryIndex" : 0,
					"id" : "all_qmllint::@6890427a1f51a3e7e1df",
					"jsonFile" : "target-all_qmllint-Debug-a97e1ea957229a69be31.json",
					"name" : "all_qmllint",
					"projectIndex" : 0
				},
				{
					"directoryIndex" : 0,
					"id" : "all_qmllint_json::@6890427a1f51a3e7e1df",
					"jsonFile" : "target-all_qmllint_json-Debug-a9c3a9d97caf864f9f2d.json",
					"name" : "all_qmllint_json",
					"projectIndex" : 0
				},
				{
					"directoryIndex" : 0,
					"id" : "all_qmllint_module::@6890427a1f51a3e7e1df",
					"jsonFile" : "target-all_qmllint_module-Debug-6b45c79247a64755fb25.json",
					"name" : "all_qmllint_module",
					"projectIndex" : 0
				},
				{
					"directoryIndex" : 0,
					"id" : "all_qmltyperegistrations::@6890427a1f51a3e7e1df",
					"jsonFile" : "target-all_qmltyperegistrations-Debug-d33092a8352be88f75b3.json",
					"name" : "all_qmltyperegistrations",
					"projectIndex" : 0
				},
				{
					"directoryIndex" : 0,
					"id" : "appRecipe-Manager::@6890427a1f51a3e7e1df",
					"jsonFile" : "target-appRecipe-Manager-Debug-790a0e2982adb1495626.json",
					"name" : "appRecipe-Manager",
					"projectIndex" : 0
				},
				{
					"directoryIndex" : 0,
					"id" : "appRecipe-Manager_autogen::@6890427a1f51a3e7e1df",
					"jsonFile" : "target-appRecipe-Manager_autogen-Debug-b33f12ec9fcaab05b479.json",
					"name" : "appRecipe-Manager_autogen",
					"projectIndex" : 0
				},
				{
					"directoryIndex" : 0,
					"id" : "appRecipe-Manager_autogen_timestamp_deps::@6890427a1f51a3e7e1df",
					"jsonFile" : "target-appRecipe-Manager_autogen_timestamp_deps-Debug-88889d50804995c0241c.json",
					"name" : "appRecipe-Manager_autogen_timestamp_deps",
					"projectIndex" : 0
				},
				{
					"directoryIndex" : 0,
					"id" : "appRecipe-Manager_copy_qml::@6890427a1f51a3e7e1df",
					"jsonFile" : "target-appRecipe-Manager_copy_qml-Debug-971afa6d02936a168861.json",
					"name" : "appRecipe-Manager_copy_qml",
					"projectIndex" : 0
				},
				{
					"directoryIndex" : 0,
					"id" : "appRecipe-Manager_copy_res::@6890427a1f51a3e7e1df",
					"jsonFile" : "target-appRecipe-Manager_copy_res-Debug-175f15430092714a1a72.json",
					"name" : "appRecipe-Manager_copy_res",
					"projectIndex" : 0
				},
				{
					"directoryIndex" : 0,
					"id" : "appRecipe-Manager_qmlimportscan::@6890427a1f51a3e7e1df",
					"jsonFile" : "target-appRecipe-Manager_qmlimportscan-Debug-f93ca2d6b7d0fd778508.json",
					"name" : "appRecipe-Manager_qmlimportscan",
					"projectIndex" : 0
				},
				{
					"directoryIndex" : 0,
					"id" : "appRecipe-Manager_qmllint::@6890427a1f51a3e7e1df",
					"jsonFile" : "target-appRecipe-Manager_qmllint-Debug-c1e7139a7f4ee2e0f0e4.json",
					"name" : "appRecipe-Manager_qmllint",
					"projectIndex" : 0
				},
				{
					"directoryIndex" : 0,
					"id" : "appRecipe-Manager_qmllint_json::@6890427a1f51a3e7e1df",
					"jsonFile" : "target-appRecipe-Manager_qmllint_json-Debug-51cf3d870a2bf83cd8d6.json",
					"name" : "appRecipe-Manager_qmllint_json",
					"projectIndex" : 0
				},
				{
					"directoryIndex" : 0,
					"id" : "appRecipe-Manager_qmllint_module::@6890427a1f51a3e7e1df",
					"jsonFile" : "target-appRecipe-Manager_qmllint_module-Debug-2495d154c379ee7358ff.json",
					"name" : "appRecipe-Manager_qmllint_module",
					"projectIndex" : 0
				},
				{
					"directoryIndex" : 0,
					"id" : "appRecipe-Manager_qmltyperegistration::@6890427a1f51a3e7e1df",
					"jsonFile" : "target-appRecipe-Manager_qmltyperegistration-Debug-81462c7e87ef578e2aac.json",
					"name" : "appRecipe-Manager_qmltyperegistration",
					"projectIndex" : 0
				},
				{
					"directoryIndex" : 0,
					"id" : "module_appRecipe-Manager_aotstats_target::@6890427a1f51a3e7e1df",
					"jsonFile" : "target-module_appRecipe-Manager_aotstats_target-Debug-a0f38ec9284f8c9ae98b.json",
					"name" : "module_appRecipe-Manager_aotstats_target",
					"projectIndex" : 0
				}
			]
		}
	],
	"kind" : "codemodel",
	"paths" : 
	{
		"build" : "/home/LeGusto/Documents/Recipe-Manager/build/Desktop-Debug",
		"source" : "/home/LeGusto/Documents/Recipe-Manager"
	},
	"version" : 
	{
		"major" : 2,
		"minor" : 7
	}
}
